com/__init__.py
com/danilo/__init__.py
com/danilo/checkmypass.py
password_leak_verifier-0.1.1.dist-info/METADATA
password_leak_verifier-0.1.1.dist-info/WHEEL
password_leak_verifier-0.1.1.dist-info/top_level.txt
password_leak_verifier-0.1.1.dist-info/RECORD
