Metadata-Version: 2.4
Name: password_leak_verifier
Version: 0.1.1
Summary: Library for password checking. It checks the number of time the password has been leaked based on pwnedpasswords records.
Home-page: https://github.com/rapzodo/password_checker
Author: Danilo De Castro
Author-email: danilocastro81@gmail.com
License: MIT
Classifier: Programming Language :: Python :: 3
Classifier: License :: OSI Approved :: MIT License
Classifier: Operating System :: OS Independent
Requires-Python: >=3.6
Requires-Dist: requests>=2.32.0
Dynamic: author
Dynamic: author-email
Dynamic: classifier
Dynamic: description
Dynamic: description-content-type
Dynamic: home-page
Dynamic: license
Dynamic: requires-dist
Dynamic: requires-python
Dynamic: summary
